.coveragerc
.gitignore
.travis.yml
LICENSE
README.rst
setup.py
bash_completion.d/rhcephpkg.bash
bin/rhcephpkg
rhcephpkg/__init__.py
rhcephpkg/build.py
rhcephpkg/changelog.py
rhcephpkg/checkout_from_patches.py
rhcephpkg/clone.py
rhcephpkg/download.py
rhcephpkg/gitbz.py
rhcephpkg/hello.py
rhcephpkg/list_builds.py
rhcephpkg/localbuild.py
rhcephpkg/log.py
rhcephpkg/main.py
rhcephpkg/merge_patches.py
rhcephpkg/new_version.py
rhcephpkg/patch.py
rhcephpkg/source.py
rhcephpkg/upload.py
rhcephpkg/util.py
rhcephpkg/watch_build.py
rhcephpkg.egg-info/PKG-INFO
rhcephpkg.egg-info/SOURCES.txt
rhcephpkg.egg-info/dependency_links.txt
rhcephpkg.egg-info/not-zip-safe
rhcephpkg.egg-info/pbr.json
rhcephpkg.egg-info/requires.txt
rhcephpkg.egg-info/top_level.txt
rhcephpkg/tests/test_build.py
rhcephpkg/tests/test_clone.py
rhcephpkg/tests/test_download.py
rhcephpkg/tests/test_hello.py
rhcephpkg/tests/test_localbuild.py
rhcephpkg/tests/test_merge_patches.py
rhcephpkg/tests/test_patch.py
rhcephpkg/tests/test_source.py
rhcephpkg/tests/test_util.py
rhcephpkg/tests/fixtures/.rhcephpkg.conf