Metadata-Version: 1.0
Name: rhcephpkg
Version: 1.13.0
Summary: Packaging tool for Red Hat Ceph Storage product
Home-page: https://github.com/red-hat-storage/rhcephpkg
Author: Ken Dreyer
Author-email: kdreyer@redhat.com
License: MIT
Keywords: packaging,build,rpkg
Platform: UNKNOWN
